rail/creation/engines/fsps_photometry_creator.py
rail/creation/engines/fsps_sed_modeler.py
rail/examples_data/creation_data/data/fsps_default_data/input_galaxy_properties_fsps.hdf5
rail/examples_data/creation_data/data/fsps_default_data/lsf_bad_wave_array.dat
rail/examples_data/creation_data/data/fsps_default_data/model_FSPSSedModeler.hdf5
rail/examples_data/creation_data/data/fsps_default_data/rail_fsps_test_sfh.txt
rail/examples_data/creation_data/data/fsps_default_data/sfh_bad_age_array.dat
rail/examples_data/creation_data/data/fsps_default_data/test_fsps_sed.fits
rail/examples_data/creation_data/data/fsps_default_data/filters/bass_g_transmission.h5
rail/examples_data/creation_data/data/fsps_default_data/filters/bass_r_transmission.h5
rail/examples_data/creation_data/data/fsps_default_data/filters/lsst_g_transmission.h5
rail/examples_data/creation_data/data/fsps_default_data/filters/lsst_i_transmission.h5
rail/examples_data/creation_data/data/fsps_default_data/filters/lsst_r_transmission.h5
rail/examples_data/creation_data/data/fsps_default_data/filters/lsst_u_transmission.h5
rail/examples_data/creation_data/data/fsps_default_data/filters/lsst_y_transmission.h5
rail/examples_data/creation_data/data/fsps_default_data/filters/lsst_z_transmission.h5
rail/examples_data/creation_data/data/fsps_default_data/filters/mzls_z_transmission.h5
rail/examples_data/creation_data/data/fsps_default_data/filters/suprimecam_b_transmission.h5
rail/examples_data/creation_data/data/fsps_default_data/filters/suprimecam_g_transmission.h5
rail/examples_data/creation_data/data/fsps_default_data/filters/suprimecam_i_transmission.h5
rail/examples_data/creation_data/data/fsps_default_data/filters/suprimecam_r_transmission.h5
rail/examples_data/creation_data/data/fsps_default_data/filters/suprimecam_v_transmission.h5
rail/examples_data/creation_data/data/fsps_default_data/filters/suprimecam_z_transmission.h5
rail/fsps/__init__.py
rail/fsps/_version.py
pz_rail_fsps-1.1.1.dist-info/LICENSE
pz_rail_fsps-1.1.1.dist-info/METADATA
pz_rail_fsps-1.1.1.dist-info/WHEEL
pz_rail_fsps-1.1.1.dist-info/top_level.txt
pz_rail_fsps-1.1.1.dist-info/RECORD
