Metadata-Version: 2.2
Name: pz-rail-fsps
Version: 1.1.1
Author-email: "LSST Dark Energy Science Collaboration (DESC)" <lsst-desc-rail-admin@slac.stanford.edu>
License: MIT License
Classifier: Development Status :: 4 - Beta
Classifier: License :: OSI Approved :: MIT License
Classifier: Intended Audience :: Developers
Classifier: Intended Audience :: Science/Research
Classifier: Operating System :: OS Independent
Classifier: Programming Language :: Python
Requires-Python: >=3.9
License-File: LICENSE
Requires-Dist: fsps
Requires-Dist: pz-rail-base>=1.0.3
Requires-Dist: astropy
Requires-Dist: h5py
Provides-Extra: dev
Requires-Dist: qp-prob[full]; extra == "dev"
Requires-Dist: coverage; extra == "dev"
Requires-Dist: pytest; extra == "dev"
Requires-Dist: pytest-cov; extra == "dev"
Requires-Dist: pre-commit; extra == "dev"
Requires-Dist: pylint; extra == "dev"
